journalpdfscraper/BMJSoupScraper.py
journalpdfscraper/Base.py
journalpdfscraper/BaseSoup.py
journalpdfscraper/ElsevierScraper.py
journalpdfscraper/JournalScraper.py
journalpdfscraper/OxfordScraper.py
journalpdfscraper/ScienceDirectScraper.py
journalpdfscraper/__init__.py
journalpdfscraper-0.2.1.dist-info/LICENSE.md
journalpdfscraper-0.2.1.dist-info/METADATA
journalpdfscraper-0.2.1.dist-info/WHEEL
journalpdfscraper-0.2.1.dist-info/top_level.txt
journalpdfscraper-0.2.1.dist-info/RECORD
