Metadata-Version: 2.1
Name: journalpdfscraper
Version: 0.2.1
Summary: A project to check if articles are free or paid
Home-page: https://github.com/PeterMorrison1/JournalPDFScraper/
Author: PeterMorrison1
License: UNKNOWN
Platform: UNKNOWN
Classifier: Programming Language :: Python :: 3
Requires-Python: >=3.6
Requires-Dist: beautifulsoup4
Requires-Dist: selenium
Requires-Dist: urllib3
Requires-Dist: requests
Requires-Dist: webdriver-manager
